template_pptx_jinja/__init__.py
template_pptx_jinja/pictures.py
template_pptx_jinja/render.py
template_pptx_jinja_fix-0.0.8.dist-info/LICENSE
template_pptx_jinja_fix-0.0.8.dist-info/METADATA
template_pptx_jinja_fix-0.0.8.dist-info/WHEEL
template_pptx_jinja_fix-0.0.8.dist-info/top_level.txt
template_pptx_jinja_fix-0.0.8.dist-info/RECORD
