Metadata-Version: 2.1
Name: template-pptx-jinja-fix
Version: 0.0.8
Summary: PowerPoint presentation builder from template using Jinja2
Home-page: https://github.com/macheal/template-pptx-jinja
Author: wlx
Author-email: 409673593@qq.com
License: UNKNOWN
Keywords: powerpoint,ppt,pptx,template
Platform: UNKNOWN
Classifier: Development Status :: 4 - Beta
Classifier: Topic :: Utilities
Classifier: Programming Language :: Python :: 3
Classifier: License :: OSI Approved :: GNU General Public License v3 (GPLv3)
Classifier: Operating System :: OS Independent
Requires-Dist: Jinja2 (==3.1.2)
Requires-Dist: python-pptx (==0.6.21)
Requires-Dist: templatepptx (==0.0.8)
